Metadata-Version: 1.1
Name: qishi-dogs
Version: 0.1
Summary: test description
Home-page: https://github.com/BlueHosts
Author: qishi
Author-email: hongfeizhan@qq.com
License: BSD
Platform: UNKNOWN
Classifier: Development Status :: 3 - Alpha
Classifier: Environment :: Web Environment
Classifier: Intended Audience :: Developers
Classifier: License :: OSI Approved :: BSD License
Classifier: Operating System :: OS Independent
Classifier: Programming Language :: Python
Classifier: Framework :: Django
